concall_tools.py
speakers/__init__.py
speakers/extraction.py
concall_tools-0.6.1.dist-info/LICENSE
concall_tools-0.6.1.dist-info/METADATA
concall_tools-0.6.1.dist-info/WHEEL
concall_tools-0.6.1.dist-info/top_level.txt
concall_tools-0.6.1.dist-info/RECORD
