Metadata-Version: 2.1
Name: concall-tools
Version: 0.6.1
Summary: Tools to extract information from concall transcripts
Author-email: Mittal Analytics Pvt Ltd <pratyush@hey.com>
License: GNU GENERAL PUBLIC LICENSE
Project-URL: Homepage, https://github.com/Mittal-Analytics/concall-tools
Requires-Python: >=3.9
License-File: LICENSE
Requires-Dist: pymupdf
Requires-Dist: nltk
Requires-Dist: numpy
Requires-Dist: lxml
Requires-Dist: cssselect
Provides-Extra: dev
Requires-Dist: pip-tools ; extra == 'dev'
Requires-Dist: flake8 ; extra == 'dev'
Requires-Dist: black ; extra == 'dev'
Requires-Dist: ipdb ; extra == 'dev'
Requires-Dist: bumpver ; extra == 'dev'
Requires-Dist: build ; extra == 'dev'
Requires-Dist: twine ; extra == 'dev'
